estuaire/__init__.py
estuaire/raytrace.cpython-311-x86_64-linux-gnu.so
estuaire/solver.cpython-311-x86_64-linux-gnu.so
estuaire/core/__init__.py
estuaire/core/data.py
estuaire/core/decorators.py
estuaire/core/frechet.py
estuaire/core/linear.py
src/estuaire/__init__.py
tests/test_sparse_sensitivity.py
tests/validate_eikonal_frechet.py
tests/validate_sparse_sensitivity.py
estuaire-1.0.3.dist-info/METADATA
estuaire-1.0.3.dist-info/WHEEL
estuaire-1.0.3.dist-info/top_level.txt
estuaire-1.0.3.dist-info/RECORD
estuaire-1.0.3.dist-info/licenses/LICENSE
